{
	"addons": {
		"addon": {
			"kind": "mod",
			"versions": [
				{
					"content_versions": "2.0.0-1.18.2",
					"minecraft_versions": "1.18.2",
					"modloaders": "quilt",
					"stability": "stable",
					"url": "https://cdn.modrinth.com/data/HMNV4z01/versions/2.0.0%2B1.18.2_quilt/feature_nbt_deadlock_be_gone_quilt-2.0.0%2B1.18.2.jar",
					"version": "sPKan8lZ"
				},
				{
					"content_versions": "2.0.0-1.18.2",
					"minecraft_versions": "1.18.2",
					"modloaders": "forgelike",
					"stability": "stable",
					"url": "https://cdn.modrinth.com/data/HMNV4z01/versions/2.0.0%2B1.18.2_forge/feature_nbt_deadlock_be_gone_forge-2.0.0%2B1.18.2.jar",
					"version": "J0MaAT8x"
				},
				{
					"content_versions": "2.0.0-1.18.2-rc1",
					"minecraft_versions": "1.18.2",
					"modloaders": "fabriclike",
					"stability": "stable",
					"url": "https://cdn.modrinth.com/data/HMNV4z01/versions/2.0.0%2B1.18.2-rc1_fabric/feature_nbt_deadlock_be_gone_fabric-2.0.0%2B1.18.2-rc1.jar",
					"version": "AJQcpbQc"
				},
				{
					"content_versions": "1.0.1-1.18.1",
					"minecraft_versions": "1.18.1",
					"modloaders": "fabriclike",
					"stability": "stable",
					"url": "https://cdn.modrinth.com/data/HMNV4z01/versions/1.0.1%2B1.18.1_fabric/feature_nbt_deadlock_be_gone_fabric-1.0.1%2B1.18.1.jar",
					"version": "isMHA16w"
				},
				{
					"content_versions": "1.0.0-1.18.1",
					"minecraft_versions": "1.18.1",
					"modloaders": "fabriclike",
					"stability": "stable",
					"url": "https://cdn.modrinth.com/data/HMNV4z01/versions/1.0.0%2B1.18.1%2Bfabric/feature_nbt_deadlock_be_gone_fabric-1.0.0%2B1.18.1.jar",
					"version": "yTW6pwUk"
				},
				{
					"content_versions": "1.0.0-1.18.1",
					"minecraft_versions": "1.18.1",
					"modloaders": "forgelike",
					"stability": "stable",
					"url": "https://cdn.modrinth.com/data/HMNV4z01/versions/1.0.0%2B1.18.1/feature_nbt_deadlock_be_gone_forge-1.0.0%2B1.18.1.jar",
					"version": "2yMhYqIL"
				}
			]
		}
	},
	"meta": {
		"authors": [
			"TelepathicGrunt"
		],
		"community": "https://discord.gg/K8qRev3yKZ",
		"description": "Fixes deadlocks caused by https://bugs.mojang.com/browse/MC-246262",
		"gallery": [],
		"icon": "https://cdn.modrinth.com/data/HMNV4z01/icon.png",
		"issues": "https://github.com/TelepathicGrunt/FeatureNBTDeadlockBeGone/issues",
		"license": "MIT",
		"long_description": "### This mod's sole goal is to fix this bug that only exists for 1.18 MC: https://bugs.mojang.com/browse/MC-246262\n\n-----\n\nThe bug is when placing NBT builds into the world during worldgen, it can deadlock the game if the build is replacing a BlockEntity of any kind. Spawners, chests, lecterns, beds, signs, etc. Which is... bad. Your game locks up and freezes. Ticks are no longer being run. \n\n \n\nThe issue comes down to the fact that the method used to place build's blocks in the world is not worldgen safe. It is using the wrong world object inside. The way this mod fixes the bug is by simply skipping the calls to those unsafe methods if the world passed into the nbt placing method is a WorldGenRegion class. More info and in-depth detail is in the bug report above. \n\n \n\nFor mods, this bug may occur more often which is why it may be a good idea to just have this mod on as a precaution. \n\n \n\nThis bug does not occur in 1.17.x and below. It is fixed in 1.19 and above. It seems to only exist in 1.18.x. \n\n \n\n------------------------------------------\n\n### MOD DEVERLOPERS:\n\n\nTo use in dev, add this to the repositories block in build.gradle:\n\n```\n    maven {\n\n       // FeatureNBTDeadlockBeGone\n\n       url \"https://nexus.resourcefulbees.com/repository/maven-public/\"   \n\n    }\n```\n\nThen in dependencies block in build.gradle, add:\n\n     FORGE:\n\n        `runtimeOnly fg.deobf(\"com.telepathicgrunt:FeatureNBTDeadlockBeGone-Forge:2.0.0+1.18.2\")`\n\n     FABRIC:\n\n        `modRuntimeOnly \"com.telepathicgrunt:FeatureNBTDeadlockBeGone-Fabric:2.0.0+1.18.2\"`\n\n     QUILT:\n\n        `modRuntimeOnly \"com.telepathicgrunt:FeatureNBTDeadlockBeGone-Quilt:2.0.0+1.18.2\"`\n\n\nChange 2.0.0+1.18.2 to the version you want.",
		"name": "Feature NBT Deadlock Be Gone",
		"package_maintainers": [
			"mcvm"
		],
		"source": "https://github.com/TelepathicGrunt/FeatureNBTDeadlockBeGone",
		"support_link": "https://ko-fi.com/telepathicgrunt"
	},
	"properties": {
		"content_versions": [
			"2.0.0-1.18.2",
			"2.0.0-1.18.2-rc1",
			"1.0.1-1.18.1",
			"1.0.0-1.18.1"
		],
		"modrinth_id": "HMNV4z01",
		"supported_modloaders": [
			"fabriclike",
			"forgelike"
		],
		"supported_sides": [
			"server"
		],
		"supported_versions": [
			"1.18.1",
			"1.18.2"
		]
	}
}