{
	"addons": {
		"addon": {
			"kind": "mod",
			"versions": [
				{
					"content_versions": "1.7.0",
					"minecraft_versions": "1.21.4",
					"modloaders": [
						"fabriclike",
						"quilt"
					],
					"relations": {
						"dependencies": "fabriclike-api"
					},
					"stability": "stable",
					"url": "https://cdn.modrinth.com/data/68kWHuUF/versions/H7ANDtwL/universal_ores-v1.7.0.jar",
					"version": "H7ANDtwL"
				},
				{
					"content_versions": "1.6.1",
					"minecraft_versions": "1.21.1",
					"modloaders": [
						"fabriclike",
						"quilt"
					],
					"relations": {
						"dependencies": "fabriclike-api"
					},
					"stability": "stable",
					"url": "https://cdn.modrinth.com/data/68kWHuUF/versions/n0hOKzrC/universal_ores-v1.6.1.jar",
					"version": "n0hOKzrC"
				},
				{
					"content_versions": "1.6.0",
					"minecraft_versions": "1.21.1",
					"modloaders": [
						"fabriclike",
						"quilt"
					],
					"relations": {
						"dependencies": "fabriclike-api"
					},
					"stability": "stable",
					"url": "https://cdn.modrinth.com/data/68kWHuUF/versions/SnWmZ7Aa/universal_ores-v1.6.0.jar",
					"version": "SnWmZ7Aa"
				},
				{
					"content_versions": "v1.5.2",
					"minecraft_versions": [
						"1.20",
						"1.20.1"
					],
					"modloaders": [
						"fabriclike",
						"quilt"
					],
					"relations": {
						"dependencies": [
							"dawn-api",
							"fabriclike-api"
						]
					},
					"stability": "stable",
					"url": "https://cdn.modrinth.com/data/68kWHuUF/versions/bEdg7gJy/universal_ores-1.5.2.jar",
					"version": "bEdg7gJy"
				},
				{
					"content_versions": "1.5.1",
					"minecraft_versions": "1.19.4",
					"modloaders": [
						"fabriclike",
						"quilt"
					],
					"relations": {
						"dependencies": [
							"dawn-api",
							"fabriclike-api"
						]
					},
					"stability": "stable",
					"url": "https://cdn.modrinth.com/data/68kWHuUF/versions/yfaaThUO/universal_ores-1.5.1.jar",
					"version": "yfaaThUO"
				},
				{
					"content_versions": "1.5.0",
					"minecraft_versions": "1.19.3",
					"modloaders": [
						"fabriclike",
						"quilt"
					],
					"relations": {
						"dependencies": [
							"dawn-api",
							"fabriclike-api"
						]
					},
					"stability": "stable",
					"url": "https://cdn.modrinth.com/data/68kWHuUF/versions/AGTMwpCI/universal_ores-1.5.0.jar",
					"version": "AGTMwpCI"
				},
				{
					"content_versions": "1.3.1",
					"minecraft_versions": [
						"1.18",
						"1.18.1",
						"1.18.2"
					],
					"modloaders": "fabriclike",
					"relations": {
						"dependencies": [
							"dawn-api",
							"fabriclike-api"
						]
					},
					"stability": "stable",
					"url": "https://cdn.modrinth.com/data/68kWHuUF/versions/1.3.1/universal_ores-1.3.1.jar",
					"version": "ST3kXuRg"
				},
				{
					"content_versions": "1.4.2",
					"minecraft_versions": [
						"1.19",
						"1.19.1",
						"1.19.2"
					],
					"modloaders": "fabriclike",
					"relations": {
						"dependencies": [
							"dawn-api",
							"fabriclike-api"
						]
					},
					"stability": "stable",
					"url": "https://cdn.modrinth.com/data/68kWHuUF/versions/1.4.2/universal_ores-1.4.2.jar",
					"version": "rbYMIYTX"
				},
				{
					"content_versions": "1.4.1",
					"minecraft_versions": "1.19",
					"modloaders": "fabriclike",
					"relations": {
						"dependencies": [
							"dawn-api",
							"fabriclike-api"
						]
					},
					"stability": "stable",
					"url": "https://cdn.modrinth.com/data/68kWHuUF/versions/1.4.1/universal_ores-1.4.1.jar",
					"version": "ZUBHa8ko"
				},
				{
					"content_versions": "1.4.0",
					"minecraft_versions": "1.19",
					"modloaders": "fabriclike",
					"relations": {
						"dependencies": [
							"dawn-api",
							"fabriclike-api"
						]
					},
					"stability": "stable",
					"url": "https://cdn.modrinth.com/data/68kWHuUF/versions/1.4.0/universal_ores-1.4.0.jar",
					"version": "iSAOElLH"
				},
				{
					"content_versions": "1.3.0",
					"minecraft_versions": [
						"1.18",
						"1.18.1",
						"1.18.2"
					],
					"modloaders": "fabriclike",
					"relations": {
						"dependencies": [
							"dawn-api",
							"fabriclike-api"
						]
					},
					"stability": "stable",
					"url": "https://cdn.modrinth.com/data/68kWHuUF/versions/1.3.0/universal_ores-1.3.0.jar",
					"version": "b18AFuxC"
				},
				{
					"content_versions": "1.2.1",
					"minecraft_versions": [
						"1.18",
						"1.18.1",
						"1.18.2"
					],
					"modloaders": "fabriclike",
					"stability": "stable",
					"url": "https://cdn.modrinth.com/data/68kWHuUF/versions/1.2.1/universal_ores-1.2.1.jar",
					"version": "PhHmCAjb"
				},
				{
					"content_versions": "1.2.0",
					"minecraft_versions": [
						"1.18",
						"1.18.1"
					],
					"modloaders": "fabriclike",
					"stability": "stable",
					"url": "https://cdn.modrinth.com/data/68kWHuUF/versions/1.2.0/universal_ores-1.2.0.jar",
					"version": "nA2h8iOk"
				},
				{
					"content_versions": "1.1.0",
					"minecraft_versions": "1.18",
					"modloaders": "fabriclike",
					"stability": "stable",
					"url": "https://cdn.modrinth.com/data/68kWHuUF/versions/1.1.0/universal_ores-1.1.0.jar",
					"version": "xS5SIDoi"
				},
				{
					"content_versions": "1.0",
					"minecraft_versions": [
						"1.17",
						"1.17.1"
					],
					"modloaders": "fabriclike",
					"stability": "stable",
					"url": "https://cdn.modrinth.com/data/68kWHuUF/versions/1.0/universal_ores-1.0.jar",
					"version": "xah6q3JR"
				}
			]
		}
	},
	"meta": {
		"authors": [
			"Hugman"
		],
		"community": "https://discord.gg/8ksTVJu",
		"description": "Adds ores variants for andesite, diorite, granite and tuff",
		"documentation": "https://dawnteammc.github.io/universal_ores",
		"gallery": [],
		"icon": "https://cdn.modrinth.com/data/68kWHuUF/icon.png",
		"issues": "https://github.com/DawnTeamMC/UniversalOres/issues",
		"license": "LicenseRef-Polyform-Shield-1.0.0",
		"long_description": "[![Universal Ores](https://dawnteammc.github.io/universal_ores/images/header.png)](https://dawnteammc.github.io/universal_ores)\n\n[![Latest release](https://img.shields.io/github/release/DawnTeamMC/UniversalOres.svg?label=Latest%20version&style=for-the-badge)](https://github.com/DawnTeamMC/UniversalOres/releases/latest)\n\n[![Discord user count](https://img.shields.io/discord/504608980799062036?label=&color=424549&labelColor=7289da&style=for-the-badge&logo=Discord&logoColor=DDE4EF)](https://discord.gg/8ksTVJu)\n[![X (formerly Twitter) Follow](https://img.shields.io/twitter/follow/DawnTeamMC?style=for-the-badge&labelColor=424549&color=424549&logo=x)](https://twitter.com/DawnTeamMC)\n\nUniversal Ores is a mod for the latest version of Minecraft that adds new vanilla ores variants for andesite, \ndiorite, granite, tuff, calcite, blackstone and basalt that generate naturally where they should precisely be.\n\n**You can visit the [official website for Universal Ores for more information](https://dawnteammc.github.io/universal_ores).**\n\n## 📦 Download\n\n⚠ Universal Ores **requires** Fabric API to be\ninstalled: [GitHub](https://github.com/FabricMC/fabric) / [CurseForge](https://www.curseforge.com/minecraft/mc-mods/fabric-api) / [Modrinth](https://modrinth.com/mod/fabric-api)\n\n## ❤️ Support\n[![Patreon supporters](https://img.shields.io/endpoint.svg?url=https%3A%2F%2Fshieldsio-patreon.vercel.app%2Fapi%3Fusername%3DHugman%26type%3Dpatrons&style=flat-square)](https://patreon.com/Hugman)\n\nYou can support Universal Ores on the [Patreon page of the founder, main developer and maintainer of the Dawn Team mods (Hugman)](https://patreon.com/Hugman).\n\nBy supporting Hugman, you can get access to the following:\n\n- Vote for the next features to be added to the Dawn Team mods\n- Get exclusive screenshots of the next features to be added to Dawn Team mods\n- Get early access to the latest beta versions of Dawn Team mods with new features\n- Get early access to new mods from the Dawn Team mods\n\n**We do not want to lock any in-game feature of the Dawn Team mods behind a paywall, because we believe that any Minecraft mod should forever remain free to download and fully exploit/use.**  \nSupporting via Patreon is a more of way to help Hugman to continue to improve the mods and show the gratitude you might have towards Hugman's work.\nSome money you donate may be used to pay for new features, such as music or art, but not all of it.",
		"name": "Universal Ores",
		"package_maintainers": [
			"mcvm"
		],
		"source": "https://github.com/DawnTeamMC/UniversalOres",
		"support_link": "https://patreon.com/Hugman"
	},
	"properties": {
		"content_versions": [
			"1.7.0",
			"1.6.1",
			"1.6.0",
			"v1.5.2",
			"1.5.1",
			"1.5.0",
			"1.4.2",
			"1.4.1",
			"1.4.0",
			"1.3.1",
			"1.3.0",
			"1.2.1",
			"1.2.0",
			"1.1.0",
			"1.0"
		],
		"modrinth_id": "68kWHuUF",
		"supported_modloaders": [
			"fabriclike"
		],
		"supported_sides": [
			"client",
			"server"
		],
		"supported_versions": [
			"1.17",
			"1.17.1",
			"1.18",
			"1.18.1",
			"1.18.2",
			"1.19",
			"1.19.1",
			"1.19.2",
			"1.19.3",
			"1.19.4",
			"1.20",
			"1.20.1",
			"1.21.1",
			"1.21.4"
		]
	}
}